agenteval/__init__.py
agenteval/cli.py
agenteval/conversation.py
agenteval/defaults.py
agenteval/hook.py
agenteval/metrics.py
agenteval/summary.py
agenteval/trace.py
agenteval/evaluators/__init__.py
agenteval/evaluators/base_evaluator.py
agenteval/evaluators/evaluator_factory.py
agenteval/evaluators/bedrock_request/__init__.py
agenteval/evaluators/bedrock_request/bedrock_request_handler.py
agenteval/evaluators/canonical/__init__.py
agenteval/evaluators/canonical/evaluator.py
agenteval/evaluators/model_config/__init__.py
agenteval/evaluators/model_config/bedrock_model_config.py
agenteval/evaluators/model_config/preconfigured_model_configs.py
agenteval/plan/__init__.py
agenteval/plan/exceptions.py
agenteval/plan/logging.py
agenteval/plan/plan.py
agenteval/targets/__init__.py
agenteval/targets/base_target.py
agenteval/targets/boto3_target.py
agenteval/targets/target_factory.py
agenteval/targets/target_response.py
agenteval/targets/bedrock_agent/__init__.py
agenteval/targets/bedrock_agent/target.py
agenteval/targets/bedrock_flow/__init__.py
agenteval/targets/bedrock_flow/target.py
agenteval/targets/bedrock_knowledge_base/__init__.py
agenteval/targets/bedrock_knowledge_base/target.py
agenteval/targets/lexv2/__init__.py
agenteval/targets/lexv2/target.py
agenteval/targets/q_business/__init__.py
agenteval/targets/q_business/target.py
agenteval/targets/sagemaker_endpoint/__init__.py
agenteval/targets/sagemaker_endpoint/target.py
agenteval/targets/weni/__init__.py
agenteval/targets/weni/target.py
agenteval/templates/evaluators/canonical/runtime/generate_evaluation.jinja
agenteval/templates/evaluators/canonical/runtime/generate_initial_prompt.jinja
agenteval/templates/evaluators/canonical/runtime/generate_test_status.jinja
agenteval/templates/evaluators/canonical/runtime/generate_user_response.jinja
agenteval/templates/evaluators/canonical/system/generate_evaluation.jinja
agenteval/templates/evaluators/canonical/system/generate_initial_prompt.jinja
weni_agenteval-1.0.7.dist-info/licenses/LICENSE
weni_agenteval-1.0.7.dist-info/licenses/NOTICE
weni_agenteval-1.0.7.dist-info/METADATA
weni_agenteval-1.0.7.dist-info/WHEEL
weni_agenteval-1.0.7.dist-info/entry_points.txt
weni_agenteval-1.0.7.dist-info/top_level.txt
weni_agenteval-1.0.7.dist-info/RECORD
