Metadata-Version: 2.4
Name: weni-agenteval
Version: 1.0.7
Summary: A generative AI-powered framework for testing virtual agents.
Author-email: Weni <john.cordeiro@vtex.com>
License-Expression: Apache-2.0
Project-URL: Homepage, https://github.com/weni-ai/agent-evaluation
Project-URL: Documentation, https://github.com/weni-ai/agent-evaluation
Project-URL: Repository, https://github.com/weni-ai/agent-evaluation
Classifier: Development Status :: 4 - Beta
Classifier: Intended Audience :: Developers
Classifier: Topic :: Utilities
Classifier: Topic :: Software Development :: Testing
Classifier: Programming Language :: Python :: 3 :: Only
Classifier: Programming Language :: Python :: 3.9
Classifier: Programming Language :: Python :: 3.10
Classifier: Programming Language :: Python :: 3.11
Classifier: Programming Language :: Python :: 3.12
Requires-Python: >=3.9
License-File: LICENSE
License-File: NOTICE
Requires-Dist: pyyaml~=6.0
Requires-Dist: boto3<2.0,>=1.34.20
Requires-Dist: click~=8.0
Requires-Dist: pydantic<3.0,>=2.1.0
Requires-Dist: rich<14.0,>=13.7.0
Requires-Dist: jinja2<4.0,>=3.1.3
Requires-Dist: jsonpath-ng<2.0,>=1.6.1
Requires-Dist: websocket-client<2.0,>=1.6.0
Requires-Dist: requests==2.32.5
Provides-Extra: dev
Requires-Dist: flake8; extra == "dev"
Requires-Dist: black; extra == "dev"
Requires-Dist: isort; extra == "dev"
Requires-Dist: pytest; extra == "dev"
Requires-Dist: pytest-cov; extra == "dev"
Requires-Dist: pytest-mock; extra == "dev"
Requires-Dist: mkdocs; extra == "dev"
Requires-Dist: mkdocs-material; extra == "dev"
Requires-Dist: mkdocstrings[python]; extra == "dev"
Requires-Dist: mkdocs-click; extra == "dev"
Requires-Dist: bandit; extra == "dev"
Requires-Dist: pip-audit; extra == "dev"
Dynamic: license-file
